log_stat_config.json
log_statistics/agent.py
volttron_log_statistics-2.0.0rc0.dist-info/LICENSE
volttron_log_statistics-2.0.0rc0.dist-info/METADATA
volttron_log_statistics-2.0.0rc0.dist-info/WHEEL
volttron_log_statistics-2.0.0rc0.dist-info/entry_points.txt
volttron_log_statistics-2.0.0rc0.dist-info/RECORD
