Metadata-Version: 2.1
Name: volttron-log-statistics
Version: 2.0.0rc0
Summary: 
Home-page: https://github.com/eclipse-volttron/volttron-log-statistics
License: Apache-2.0
Author: VOLTTRON Team
Author-email: volttron@pnnl.gov
Requires-Python: >=3.10,<4.0
Classifier: Intended Audience :: Developers
Classifier: Intended Audience :: Information Technology
Classifier: Intended Audience :: Other Audience
Classifier: Intended Audience :: Science/Research
Classifier: License :: OSI Approved :: Apache Software License
Classifier: Programming Language :: Python :: 3
Classifier: Programming Language :: Python :: 3.10
Classifier: Programming Language :: Python :: 3.11
Classifier: Programming Language :: Python :: 3.12
Classifier: Programming Language :: Python :: 3 :: Only
Requires-Dist: volttron-core (>=2.0.0rc0)
Project-URL: Repository, https://github.com/eclipse-volttron/volttron-log-statistics
